my_plotly_package/__init__.py
my_plotly_package/plotly_utils.py
Ses_plotly-0.1.7.dist-info/LICENCE
Ses_plotly-0.1.7.dist-info/METADATA
Ses_plotly-0.1.7.dist-info/WHEEL
Ses_plotly-0.1.7.dist-info/top_level.txt
Ses_plotly-0.1.7.dist-info/RECORD
