Metadata-Version: 2.1
Name: Ses-plotly
Version: 0.1.7
Summary: Objetivo da criação dessas funções são para que reduza o tempo na contrução e estilização de indicadores para Futuros Dashboards utilizando poucas linhas de codigo.
Home-page: https://github.com/Diogoa83/biblioteca_python_dash
Author: Diogo Antonio
Author-email: diogoantoniodejesus@hotmail.com
Classifier: Programming Language :: Python :: 3
Classifier: License :: OSI Approved :: MIT License
Classifier: Operating System :: OS Independent
Requires-Python: >=3.6
License-File: LICENCE
Requires-Dist: plotly >=5.0.0
Requires-Dist: pandas >=1.0.0
